{"name": "SetPlayerObjectRot", "tags": ["player"], "kind": "functions", "notes": "To smoothly rotate an object, see MovePlayerObject.", "warnings": null, "versions": null, "tips": null, "outdated": null, "lowercase": null, "description": "Set the rotation of an object on the X, Y and Z axis.", "params_title": "(playerid, objectid, Float:RotX, Float:RotY, Float:RotZ)", "params_body": [{"name": "playerid", "description": "The ID of the player whose player-object to rotate."}, {"name": "objectid", "description": "The ID of the player-object to rotate."}, {"name": "Float:RotX", "description": "The X rotation to set."}, {"name": "Float:RotY", "description": "The Y rotation to set."}, {"name": "Float:RotZ", "description": "The Z rotation to set."}], "return_values": " 1: The function executed successfully. \n\n 0: The function failed to execute. ", "pawn_code": ["SetPlayerObjectRot(playerid, objectid, RotX, RotY, RotZ);"], "code": [], "related_fn": [" CreatePlayerObject: Create an object for only one player.\n", " DestroyPlayerObject: Destroy a player object.\n", " IsValidPlayerObject: Checks if a certain player object is vaild.\n", " MovePlayerObject: Move a player object.\n", " StopPlayerObject: Stop a player object from moving.\n", " SetPlayerObjectPos: Set the position of a player object.\n", " GetPlayerObjectPos: Locate a player object.\n", " GetPlayerObjectRot: Check the rotation of a player object.\n", " AttachPlayerObjectToPlayer: Attach a player object to a player.\n", " CreateObject: Create an object.\n", " DestroyObject: Destroy an object.\n", " IsValidObject: Checks if a certain object is vaild.\n", " MoveObject: Move an object.\n", " StopObject: Stop an object from moving.\n", " SetObjectPos: Set the position of an object.\n", " SetObjectRot: Set the rotation of an object.\n", " GetObjectPos: Locate an object.\n", " GetObjectRot: Check the rotation of an object.\n", " AttachObjectToPlayer: Attach an object to a player.\n"], "related_cb": []}